{
	"0": "Azure",
	"1": "General",
	"2": "PowerShell",
	"3": "Web Development",
	"4": "Azure Security",
	"5": "Azure SQL",
	"6": "Azure Script Sample",
	"7": "Azure vs AWS",
	"16": "azure",
	"17": "general",
	"18": "powershell",
	"19": "web development",
	"20": "arm",
	"21": "asm",
	"22": "mvc",
	"23": ".net",
	"24": "automation",
	"25": "sma",
	"26": "dsc",
	"27": "azureresourcemanager",
	"28": "azureservicemanagement",
	"29": "windows10",
	"30": "webdevelopment",
	"31": "desiredstateconfigurations",
	"32": "resourcemanager",
	"33": "azureautomation",
	"34": "azuresiterecovery",
	"35": "asr",
	"36": "gridmvc",
	"37": "chartjs",
	"38": "announcement",
	"39": "ad",
	"40": "activedirectory",
	"41": "csharp",
	"42": "vm",
	"43": "virtualmachine",
	"44": "storage",
	"45": "datacenter",
	"46": "blob",
	"47": "VMWare",
	"48": "ASR",
	"49": "AzureSiteRecovery",
	"50": "ARM",
	"51": "AzureResourceManager",
	"52": "Templates",
	"53": "JSON",
	"54": "VisualStudio",
	"55": "Tags",
	"56": "Sample",
	"57": "Script",
	"58": "RemoteApp",
	"59": "Automation",
	"60": "Runbooks",
	"61": "KeyVault",
	"62": "AD",
	"63": "ActiveDirectory",
	"64": "ResourceGroups",
	"65": "ApplicationInsights",
	"66": "reservedinstances",
	"67": "manageddisks",
	"68": "microsoft",
	"69": "microsoftazure",
	"70": "shell",
	"71": "certifications",
	"72": "mcsa",
	"73": "mcse",
	"74": "mcsd",
	"75": "cloud",
	"76": "bash",
	"77": "troubleshooting",
	"78": "azuresecurity",
	"79": "security",
	"80": "azue",
	"81": "oms",
	"82": "loganalytics",
	"83": "log",
	"84": "analytics",
	"85": "query",
	"86": "language",
	"87": "querylanguage",
	"88": "roles",
	"89": "customroles",
	"90": "custom",
	"91": "policies",
	"92": "azurepolicies",
	"93": "policy",
	"94": "ebook",
	"95": "book",
	"96": "templates",
	"97": "armtemplates",
	"98": "custompolicy",
	"99": "initiative",
	"100": "initiativedefinition",
	"101": "definitions",
	"102": "data",
	"103": "datasecurity",
	"104": "transparent",
	"105": "encryption",
	"106": "transparentdataencryption",
	"107": "threat",
	"108": "detection",
	"109": "audit",
	"110": "auditing",
	"111": "sql",
	"112": "azuresql",
	"113": "database",
	"114": "sqldatabase",
	"115": "compute",
	"116": "console",
	"117": "serial",
	"118": "preview",
	"119": "firewall",
	"120": "server",
	"121": "network",
	"122": "virtual",
	"123": "service",
	"124": "endpoint",
	"125": "endpoints",
	"126": "virtualnetwork",
	"127": "dynamic",
	"128": "datamask",
	"129": "mask",
	"130": "masking",
	"131": "dynamicdatamasking",
	"132": "dnamicdatamask",
	"133": "tde",
	"134": "tips",
	"135": "tricks",
	"136": "search",
	"137": "navigate",
	"138": "portal",
	"139": "azureportal",
	"140": "document",
	"141": "documentation",
	"142": "diagnose",
	"143": "bootstrap",
	"144": "command",
	"145": "series",
	"146": "webinar",
	"147": "session",
	"148": "azureawareness",
	"149": "awareness",
	"150": "march",
	"151": "format",
	"152": "script",
	"153": "sample",
	"154": "runbook",
	"155": "recovery",
	"156": "email",
	"157": "notification",
	"158": "locks",
	"159": "lock",
	"160": "rbac",
	"161": "report",
	"162": "tags",
	"163": "tag",
	"164": "resourcegroups",
	"165": "resourcegroup",
	"166": "backup",
	"167": "hub",
	"168": "licensing",
	"169": "license",
	"170": "snapshots",
	"171": "udr",
	"172": "routetables",
	"173": "subnet",
	"174": "subnets",
	"175": "routetable",
	"176": "index",
	"177": "function",
	"178": "functions",
	"179": "logic",
	"180": "app",
	"181": "appservice",
	"182": "logicapps",
	"183": "migration",
	"184": "dr",
	"185": "disasterrecovery",
	"186": "desktop",
	"187": "windows",
	"188": "virtualdesktop",
	"189": "password",
	"190": "protection",
	"191": "aws",
	"192": "ec2",
	"193": "insights",
	"194": "batch",
	"195": "scale",
	"196": "scaleset",
	"197": "vmss",
	"198": "s3",
	"199": "s3bucket",
	"200": "bucket",
	"201": "vpc",
	"202": "datafactory",
	"203": "factory",
	"204": "update",
	"205": "updates",
	"206": "azuread",
	"207": "gateway",
	"208": "waf",
	"209": "vmware",
	"210": "configuration",
	"211": "configurations",
	"212": "python",
	"213": "serverless",
	"214": "github",
	"215": "identity",
	"216": "cost",
	"217": "billing",
	"218": "ssis",
	"219": "nsg"
}